mshextras/__init__.py
mshextras/module.py
mshextras-0.4.dist-info/LICENSE
mshextras-0.4.dist-info/METADATA
mshextras-0.4.dist-info/WHEEL
mshextras-0.4.dist-info/top_level.txt
mshextras-0.4.dist-info/RECORD
