Metadata-Version: 2.1
Name: mshextras
Version: 0.4
Summary: Extra fields for Marshmallow (bugfix)
Home-page: https://github.com/bnnk/marshmallow-extras
Author: BK Shrinandhan
Author-email: python.access.server@gmail.com
License: gpl-3.0
Project-URL: Documentation, https://github.com/bnnk/marshmallow-extras/blob/master/README.md/
Project-URL: Say Thanks!, https://saythanks.io/to/bk.shrinandhan%40gmail.com/
Project-URL: Source, https://github.com/bnnk/marshmallow-extras/
Project-URL: Tracker, https://github.com/bnnk/marshmallow-extras/issues
Platform: UNKNOWN
Classifier: Development Status :: 4 - Beta
Classifier: Intended Audience :: Developers
Classifier: Programming Language :: Python :: 3
Classifier: Programming Language :: Python :: 3.4
Classifier: Programming Language :: Python :: 3.5
Classifier: Programming Language :: Python :: 3.6
Requires-Dist: numpy
Requires-Dist: pandas
Requires-Dist: pyotp
Requires-Dist: requests
Requires-Dist: furl
